uptimerobotpy/__init__.py
uptimerobotpy/__version__.py
uptimerobotpy/uptime_robot.py
uptimerobotpy-0.1.5.dist-info/LICENSE
uptimerobotpy-0.1.5.dist-info/METADATA
uptimerobotpy-0.1.5.dist-info/WHEEL
uptimerobotpy-0.1.5.dist-info/top_level.txt
uptimerobotpy-0.1.5.dist-info/RECORD
