Metadata-Version: 2.1
Name: uptimerobotpy
Version: 0.1.5
Summary: Interact with UptimeRobot API
Home-page: https://github.com/jpavlav/UptimeRobotPy
Author: Justin Palmer
Author-email: jpavlav@gmail.com
License: MIT
Platform: UNKNOWN
Classifier: License :: OSI Approved :: MIT License
Classifier: Programming Language :: Python :: 3
Classifier: Programming Language :: Python :: 3.6
Classifier: Topic :: System :: Systems Administration
Classifier: Topic :: Software Development :: Libraries
Classifier: Topic :: Software Development :: Libraries :: Python Modules
Requires-Python: >=3.5.0
Requires-Dist: requests (>=2.20.0)
